django_admin_favorite_filters/__init__.py
django_admin_favorite_filters/admin.py
django_admin_favorite_filters/apps.py
django_admin_favorite_filters/constants.py
django_admin_favorite_filters/filters.py
django_admin_favorite_filters/migrations/0001_initial.py
django_admin_favorite_filters/migrations/__init__.py
django_admin_favorite_filters/mixins.py
django_admin_favorite_filters/models.py
django_admin_favorite_filters/tests.py
django_admin_favorite_filters/views.py
django_admin_favorite_filters-0.1.0.dist-info/WHEEL
django_admin_favorite_filters-0.1.0.dist-info/METADATA
django_admin_favorite_filters-0.1.0.dist-info/RECORD
