Metadata-Version: 2.1
Name: django-admin-favorite-filters
Version: 0.1.0
Summary: 
Author: Yigit Guler
Author-email: yigit@hipo.biz
Requires-Python: >=3.7
Classifier: Programming Language :: Python :: 3
Classifier: Programming Language :: Python :: 3.7
Classifier: Programming Language :: Python :: 3.8
Requires-Dist: Django (>=2.1)
